<configs>
	<append xpath="//buff[@name='buffInjuryAbrasion']/effect_group">
		<triggered_effect trigger="onSelfBuffStart" action="ModifyCVar" target="self" cvar="wellness" operation="subtract" value="3">
		<requirement name="CVarCompare" cvar="wellness" operation="GTE" value="60"/>
		</triggered_effect>
	</append>
	<append xpath="//buff[@name='buffLegSprained']/effect_group">
		<triggered_effect trigger="onSelfBuffStart" action="ModifyCVar" target="self" cvar="wellness" operation="subtract" value="3">
		<requirement name="CVarCompare" cvar="wellness" operation="GTE" value="60"/>
		</triggered_effect>
	</append>
	<append xpath="//buff[@name='buffLegBroken']/effect_group">
		<triggered_effect trigger="onSelfBuffStart" action="ModifyCVar" target="self" cvar="wellness" operation="subtract" value="5">
		<requirement name="CVarCompare" cvar="wellness" operation="GTE" value="60"/>
		</triggered_effect>
	</append>
	<append xpath="//buff[@name='buffArmSprained']/effect_group">
		<triggered_effect trigger="onSelfBuffStart" action="ModifyCVar" target="self" cvar="wellness" operation="subtract" value="5">
		<requirement name="CVarCompare" cvar="wellness" operation="GTE" value="60"/>
		</triggered_effect>
	</append>
	<append xpath="//buff[@name='buffArmBroken']/effect_group">
		<triggered_effect trigger="onSelfBuffStart" action="ModifyCVar" target="self" cvar="wellness" operation="subtract" value="5">
		<requirement name="CVarCompare" cvar="wellness" operation="GTE" value="60"/>
		</triggered_effect>
	</append>
	<append xpath="//buff[@name='buffFatigued']/effect_group">
		<triggered_effect trigger="onSelfBuffStart" action="ModifyCVar" target="self" cvar="wellness" operation="subtract" value="3">
		<requirement name="CVarCompare" cvar="wellness" operation="GTE" value="60"/>
		</triggered_effect>
	</append>
	<append xpath="//buff[@name='buffLaceration']/effect_group">
		<triggered_effect trigger="onSelfBuffStart" action="ModifyCVar" target="self" cvar="wellness" operation="subtract" value="5">
		<requirement name="CVarCompare" cvar="wellness" operation="GTE" value="60"/>
		</triggered_effect>
	</append>
	<append xpath="//buff[@name='buffInjuryConcussion']/effect_group">
		<triggered_effect trigger="onSelfBuffStart" action="ModifyCVar" target="self" cvar="wellness" operation="subtract" value="5">
		<requirement name="CVarCompare" cvar="wellness" operation="GTE" value="60"/>
		</triggered_effect>
	</append>
	<set xpath="//buff[@name='buffNearDeathTraumaTrigger']">
		<property name="hidden" value="true"/>
		<damage_type value="disease"/>
		<stack_type value="replace"/>
		<duration value="1"/>
		<effect_group name="Failsafe to set player wellness to 50">
			<requirement name="CVarCompare" cvar="wellness" operation="LT" value="50"/>
			<triggered_effect trigger="onSelfBuffStart" action="ModifyCVar" target="self" cvar="wellness" operation="set" value="50"/>
		</effect_group>
		<effect_group name="Reducing player Wellness due to death">
			<requirement name="CVarCompare" cvar="wellness" operation="GTE" value="60"/>
			<triggered_effect trigger="onSelfBuffStart" action="ModifyCVar" target="self" cvar="wellness" operation="subtract" value="10"/>
		</effect_group>
		<effect_group>
			<passive_effect name="HealthMax" operation="base_set" value="@wellness"/>
			<passive_effect name="StaminaMax" operation="base_set" value="@wellness"/>
			<triggered_effect trigger="onSelfBuffRemove" action="AddBuff" buff="buffNearDeathRegen"/>
			<triggered_effect trigger="onSelfBuffRemove" action="AddBuff" buff="buffNearDeathTrauma"/>
		</effect_group>
	</set>
	<append xpath="/buffs">
		<buff name="buffWellnessOne" hidden="true" >
			<stack_type value="replace"/>
			<duration value="1"/>
			<effect_group name="Increasing player Wellness">
				<requirement name="CVarCompare" cvar="wellness" operation="LT" value="200"/>
				<triggered_effect trigger="onSelfBuffStart" action="ModifyCVar" target="self" cvar="wellness" operation="add" value="1"/>
			</effect_group>
			<effect_group>
				<passive_effect name="HealthMax" operation="base_set" value="@wellness"/>
				<passive_effect name="StaminaMax" operation="base_set" value="@wellness"/>
			</effect_group>
		</buff>
		<buff name="buffWellnessTwo" hidden="true" >
			<stack_type value="replace"/>
			<duration value="1"/>
			<effect_group name="Increasing player Wellness">
				<requirement name="CVarCompare" cvar="wellness" operation="LT" value="200"/>
				<triggered_effect trigger="onSelfBuffStart" action="ModifyCVar" target="self" cvar="wellness" operation="add" value="2"/>
			</effect_group>
			<effect_group>
				<passive_effect name="HealthMax" operation="base_set" value="@wellness"/>
				<passive_effect name="StaminaMax" operation="base_set" value="@wellness"/>
			</effect_group>
		</buff>
		<buff name="buffWellnessThree" hidden="true" >
			<stack_type value="replace"/>
			<duration value="1"/>
			<effect_group name="Increasing player Wellness">
				<requirement name="CVarCompare" cvar="wellness" operation="LT" value="200"/>
				<triggered_effect trigger="onSelfBuffStart" action="ModifyCVar" target="self" cvar="wellness" operation="add" value="3"/>
			</effect_group>
			<effect_group>
				<passive_effect name="HealthMax" operation="base_set" value="@wellness"/>
				<passive_effect name="StaminaMax" operation="base_set" value="@wellness"/>
			</effect_group>
		</buff>
		<buff name="buffWellnessFour" hidden="true" >
			<stack_type value="replace"/>
			<duration value="1"/>
			<effect_group name="Increasing player Wellness">
				<requirement name="CVarCompare" cvar="wellness" operation="LT" value="200"/>
				<triggered_effect trigger="onSelfBuffStart" action="ModifyCVar" target="self" cvar="wellness" operation="add" value="4"/>
			</effect_group>
			<effect_group>
				<passive_effect name="HealthMax" operation="base_set" value="@wellness"/>
				<passive_effect name="StaminaMax" operation="base_set" value="@wellness"/>
			</effect_group>
		</buff>
		<buff name="buffWellnessFive" hidden="true">
			<stack_type value="replace"/>
			<duration value="1"/>
			<effect_group name="Increasing player Wellness">
				<requirement name="CVarCompare" cvar="wellness" operation="LT" value="200"/>
				<triggered_effect trigger="onSelfBuffStart" action="ModifyCVar" target="self" cvar="wellness" operation="add" value="5"/>
			</effect_group>
			<effect_group>
				<passive_effect name="HealthMax" operation="base_set" value="@wellness"/>
				<passive_effect name="StaminaMax" operation="base_set" value="@wellness"/>
			</effect_group>
		</buff>
		<buff name="buffAverageFood" name_key="buffAverageFoodName" description_key="buffAverageFoodDesc" tooltip_key="buffAverageFoodTooltip" tags="food" icon="ui_game_symbol_hunger" hidden="false" remove_on_death="true" icon_color="66,135,245">
			<stack_type value="replace"/>
			<duration value="900"/>
			<update_rate value="30"/>
			<effect_group>
				<triggered_effect trigger="onSelfBuffUpdate" action="ModifyStats" stat="Health" operation="add" value="1"/>
				<triggered_effect trigger="onSelfBuffStart" action="AddBuff" target="self" buff="buffFoodStaminaBonus"/>
				<triggered_effect trigger="onSelfBuffStart" action="RemoveBuff" target="self" buff="buffFoodStaminaBonus2"/>
				<triggered_effect trigger="onSelfBuffStart" action="ModifyCVar" cvar="buffAverageFoodDisplay" operation="set" value="900"/>
				<triggered_effect trigger="onSelfBuffUpdate" action="ModifyCVar" cvar="buffAverageFoodDisplay" operation="subtract" value="1"/>
			</effect_group>
		</buff>
		<buff name="buffGoodFood" name_key="buffGoodFoodName" description_key="buffGoodFoodDesc" tooltip_key="buffGoodFoodTooltip" tags="food" icon="ui_game_symbol_hunger" hidden="false" remove_on_death="true" icon_color="255,153,53">
			<stack_type value="replace"/>
			<duration value="1800"/>
			<update_rate value="15"/>
			<effect_group>
				<triggered_effect trigger="onSelfBuffUpdate" action="ModifyStats" stat="Health" operation="add" value="1"/>
				<triggered_effect trigger="onSelfBuffStart" action="AddBuff" target="self" buff="buffFoodStaminaBonus2"/>
				<triggered_effect trigger="onSelfBuffStart" action="RemoveBuff" target="self" buff="buffFoodStaminaBonus"/>
				<triggered_effect trigger="onSelfBuffStart" action="ModifyCVar" cvar="buffGoodFoodDisplay" operation="set" value="1800"/>
				<triggered_effect trigger="onSelfBuffUpdate" action="ModifyCVar" cvar="buffGoodFoodDisplay" operation="subtract" value="1"/>
			</effect_group>
		</buff>
		<buff name="buffAverageDrink" name_key="buffAverageDrinkName" description_key="buffAverageDrinkDesc" tooltip_key="buffAverageDrinkTooltip" tags="drink" icon="ui_game_symbol_water" hidden="false" remove_on_death="true" icon_color="0,128,255">
			<stack_type value="replace"/>
			<duration value="900"/>
			<update_rate value="30"/>
			<effect_group>
				<triggered_effect trigger="onSelfBuffUpdate" action="ModifyStats" stat="Health" operation="add" value="1"/>
				<triggered_effect trigger="onSelfBuffStart" action="ModifyCVar" cvar="buffAverageDrinkDisplay" operation="set" value="900"/>
				<triggered_effect trigger="onSelfBuffUpdate" action="ModifyCVar" cvar="buffAverageDrinkDisplay" operation="subtract" value="1"/>
			</effect_group>
		</buff>
		<buff name="buffGoodDrink" name_key="buffGoodDrinkName" description_key="buffGoodDrinkDesc" tooltip_key="buffGoodDrinkTooltip" tags="drink" icon="ui_game_symbol_water" hidden="false" remove_on_death="true" icon_color="127,0,255">
			<stack_type value="replace"/>
			<duration value="1800"/>
			<update_rate value="20"/>
			<effect_group>
				<triggered_effect trigger="onSelfBuffUpdate" action="ModifyStats" stat="Health" operation="add" value="1"/>
				<triggered_effect trigger="onSelfBuffStart" action="ModifyCVar" cvar="buffGoodDrinkDisplay" operation="set" value="1800"/>
				<triggered_effect trigger="onSelfBuffUpdate" action="ModifyCVar" cvar="buffGoodDrinkDisplay" operation="subtract" value="1"/>
			</effect_group>
		</buff>
	</append>
</configs>

					
					
